{
  "@class" : "org.jasig.cas.services.RegexRegisteredService",
  "id" : 203948234207231,
  "name" : "Preregistration Challenge",
  "description" : "",
  "serviceId" : "^https?://(localhost|127\\.0\\.0\\.1):5000/prereg/.*",
  "evaluationOrder": "1000",
  "logo": "",
  "attributeReleasePolicy" : {
    "@class" : "org.jasig.cas.services.ReturnAllowedAttributeReleasePolicy",
    "allowedAttributes" : [
      "java.util.ArrayList", [
        "given-names", "family-name"
      ]
    ]
  },
  "properties" : {
    "@class" : "java.util.HashMap",
    "title" : {
      "@class" : "org.jasig.cas.services.DefaultRegisteredServiceProperty",
      "values" : [
        "java.util.HashSet", [
          "Open Science Framework"
        ]
      ]
    },
    "titleAbbr" : {
      "@class" : "org.jasig.cas.services.DefaultRegisteredServiceProperty",
      "values" : [
        "java.util.HashSet", [
          "OSF"
        ]
      ]
    },
    "campaign": {
      "@class" : "org.jasig.cas.services.DefaultRegisteredServiceProperty",
      "values" : [
        "java.util.HashSet", [
          "prereg"
        ]
      ]
    }
  }
}
